npmap/__init__.py
npmap/matrix.py
npmap-0.0.0.dist-info/METADATA
npmap-0.0.0.dist-info/WHEEL
npmap-0.0.0.dist-info/top_level.txt
npmap-0.0.0.dist-info/RECORD
