Metadata-Version: 2.1
Name: npmap
Version: 0.0.0
Summary: A simple tool for calculating object detection map
Author: triplemu
Author-email: gpu@163.com
Classifier: Programming Language :: Python :: 3
Classifier: License :: OSI Approved :: MIT License
Classifier: Operating System :: OS Independent
Requires-Python: >=3
Requires-Dist: numpy
